vector2dim/__init__.py
vector2dim/vector2dim.py
vector2Dim-0.1.1.dist-info/LICENSE.txt
vector2Dim-0.1.1.dist-info/METADATA
vector2Dim-0.1.1.dist-info/WHEEL
vector2Dim-0.1.1.dist-info/top_level.txt
vector2Dim-0.1.1.dist-info/RECORD
